utils_convert_LionHp192/utils/utils.py
utils_convert_LionHp192-1.1.1.dist-info/LICENSE
utils_convert_LionHp192-1.1.1.dist-info/METADATA
utils_convert_LionHp192-1.1.1.dist-info/WHEEL
utils_convert_LionHp192-1.1.1.dist-info/top_level.txt
utils_convert_LionHp192-1.1.1.dist-info/RECORD
